brown_logger/__init__.py
brown_logger/main.py
brown_logger-0.1.0.dist-info/LICENSE
brown_logger-0.1.0.dist-info/METADATA
brown_logger-0.1.0.dist-info/WHEEL
brown_logger-0.1.0.dist-info/top_level.txt
brown_logger-0.1.0.dist-info/RECORD
