Metadata-Version: 2.1
Name: brown-logger
Version: 0.1.0
Summary: A Singleton Logger implementation with console and file logging support
Home-page: https://github.com/iamlamm/brown-logger
Author: Lam
Author-email: Lam <huynhnhathanhtruc@gmail.com>
License: MIT License
Project-URL: Homepage, https://github.com/iamlamm/brown-logger
Keywords: logging,singleton,rotating-file
Classifier: Programming Language :: Python :: 3
Classifier: License :: OSI Approved :: MIT License
Classifier: Operating System :: OS Independent
Requires-Python: >=3.7
License-File: LICENSE
Provides-Extra: dev
Requires-Dist: pytest>=6.0; extra == "dev"
Requires-Dist: pytest-cov>=2.0; extra == "dev"
Requires-Dist: flake8>=3.9.0; extra == "dev"
Requires-Dist: black>=21.0; extra == "dev"
Requires-Dist: isort>=5.0; extra == "dev"
